seq2squiggle/__init.py__
seq2squiggle/__init__.py
seq2squiggle/config.yaml
seq2squiggle/dataloader.py
seq2squiggle/inference.py
seq2squiggle/layers.py
seq2squiggle/model.py
seq2squiggle/modules.py
seq2squiggle/preprocess.py
seq2squiggle/seq2squiggle.py
seq2squiggle/signal_io.py
seq2squiggle/standardize-events.py
seq2squiggle/sweep.yaml
seq2squiggle/train.py
seq2squiggle/train_sweep.py
seq2squiggle/utils.py
seq2squiggle-0.3.3.dist-info/LICENSE
seq2squiggle-0.3.3.dist-info/METADATA
seq2squiggle-0.3.3.dist-info/WHEEL
seq2squiggle-0.3.3.dist-info/entry_points.txt
seq2squiggle-0.3.3.dist-info/RECORD
