Metadata-Version: 2.1
Name: seq2squiggle
Version: 0.3.3
Summary: End-to-end simulation of nanopore sequencing signals with feed-forward transformers
Home-page: https://github.com/ZKI-PH-ImageAnalysis/seq2squiggle
License: MIT
Author: Denis Beslic
Author-email: beslicd@rki.de
Requires-Python: >=3.10,<4.0
Classifier: License :: OSI Approved :: MIT License
Classifier: Programming Language :: Python :: 3
Classifier: Programming Language :: Python :: 3.10
Classifier: Programming Language :: Python :: 3.11
Classifier: Programming Language :: Python :: 3.12
Requires-Dist: PyGithub (>=2.3.0,<3.0.0)
Requires-Dist: PyYAML (>=6.0.1,<7.0.0)
Requires-Dist: appdirs (>=1.4.4,<2.0.0)
Requires-Dist: cryptography (>=43.0.3,<44.0.0)
Requires-Dist: lightning (>=2.2.5,<3.0.0)
Requires-Dist: matplotlib (>=3.9.0,<4.0.0)
Requires-Dist: numba (>=0.59.0,<0.60.0)
Requires-Dist: numpy (>=1.26.4,<2.0.0)
Requires-Dist: pod5 (>=0.3.12,<0.4.0)
Requires-Dist: prettytable (>=3.9.0,<4.0.0)
Requires-Dist: pysam (>=0.22.0,<0.23.0)
Requires-Dist: pyslow5 (>=1.1.0,<2.0.0)
Requires-Dist: rich-click (>=1.8.2,<2.0.0)
Requires-Dist: scikit-learn (>=1.4.0,<2.0.0)
Requires-Dist: torch (>=2.6.0,<3.0.0)
Requires-Dist: tqdm (>=4.66.2,<5.0.0)
Requires-Dist: transformers (>=4.48.0,<5.0.0)
Requires-Dist: wandb (>=0.16.3,<0.17.0)
Project-URL: Repository, https://github.com/ZKI-PH-ImageAnalysis/seq2squiggle
